thisgoeshardasfuck/__init__.py
thisgoeshardasfuck-1.0.0.dist-info/LICENSE
thisgoeshardasfuck-1.0.0.dist-info/METADATA
thisgoeshardasfuck-1.0.0.dist-info/WHEEL
thisgoeshardasfuck-1.0.0.dist-info/entry_points.txt
thisgoeshardasfuck-1.0.0.dist-info/top_level.txt
thisgoeshardasfuck-1.0.0.dist-info/RECORD
