Metadata-Version: 2.1
Name: thisgoeshardasfuck
Version: 1.0.0
Summary: this goes hard as fuck.
Author-email: Joel Yisrael <joel@highlyawear.com>
License: MIT
License-File: LICENSE
